{
  "LinksList": [
    {
      "link": "https://github.com/dabi-vm/hasti-bazar-hiring-test",
      "title": "Instagram",
      "id": "cQatCg6"
    },
    {
      "link": "https://github.com/dabi-vm/hasti-bazar-hiring-test",
      "title": "Website",
      "id": "rpWRPQV"
    },
    {
      "link": "https://github.com/dabi-vm/hasti-bazar-hiring-test",
      "title": "Facebook",
      "id": "bS4GFyT"
    },
    {
      "link": "https://mui.com/material-ui/material-icons/?query=circle",
      "title": "Twitter",
      "id": "GYsPKKb"
    },
    {
      "link": "https://github.com/dabi-vm/hasti-bazar-hiring-test",
      "title": "LinkedIn",
      "id": "Ri3krmb"
    }
  ]
}